[
  {"name": "London", "lat": 51.51, "lon": -0.13},
  {"name": "Paris", "lat": 48.85, "lon": 2.35},
  {"name": "Berlin", "lat": 52.52, "lon": 13.41},
  {"name": "Rome", "lat": 41.90, "lon": 12.50},
  {"name": "Madrid", "lat": 40.42, "lon": -3.70},
  {"name": "Warsaw", "lat": 52.23, "lon": 21.01},
  {"name": "Kyiv", "lat": 50.45, "lon": 30.52},
  {"name": "Amsterdam", "lat": 52.37, "lon": 4.90},
  {"name": "Vienna", "lat": 48.21, "lon": 16.37},
  {"name": "Stockholm", "lat": 59.33, "lon": 18.07},
  {"name": "Athens", "lat": 37.98, "lon": 23.73},
  {"name": "Budapest", "lat": 47.50, "lon": 19.04},
  {"name": "Prague", "lat": 50.08, "lon": 14.44},
  {"name": "Lisbon", "lat": 38.72, "lon": -9.14},
  {"name": "Moscow", "lat": 55.75, "lon": 37.62},
  {"name": "Istanbul", "lat": 41.01, "lon": 28.97},
  {"name": "Bucharest", "lat": 44.43, "lon": 26.10},
  {"name": "Brussels", "lat": 50.85, "lon": 4.35},
  {"name": "Oslo", "lat": 59.91, "lon": 10.75},
  {"name": "Helsinki", "lat": 60.17, "lon": 24.94},
  {"name": "Copenhagen", "lat": 55.68, "lon": 12.57},
  {"name": "Zurich", "lat": 47.38, "lon": 8.54},
  {"name": "Belgrade", "lat": 44.80, "lon": 20.47},
  {"name": "Sofia", "lat": 42.70, "lon": 23.32},
  {"name": "Minsk", "lat": 53.90, "lon": 27.57},
  {"name": "New York", "lat": 40.71, "lon": -74.01},
  {"name": "Los Angeles", "lat": 34.05, "lon": -118.24},
  {"name": "Chicago", "lat": 41.88, "lon": -87.63},
  {"name": "Toronto", "lat": 43.65, "lon": -79.38},
  {"name": "Mexico City", "lat": 19.43, "lon": -99.13},
  {"name": "Vancouver", "lat": 49.25, "lon": -123.12},
  {"name": "San Francisco", "lat": 37.77, "lon": -122.42},
  {"name": "Houston", "lat": 29.76, "lon": -95.37},
  {"name": "Washington DC", "lat": 38.91, "lon": -77.04},
  {"name": "Miami", "lat": 25.77, "lon": -80.20},
  {"name": "Montreal", "lat": 45.50, "lon": -73.57},
  {"name": "Seattle", "lat": 47.61, "lon": -122.33},
  {"name": "Atlanta", "lat": 33.75, "lon": -84.39},
  {"name": "Havana", "lat": 23.14, "lon": -82.36},
  {"name": "Guatemala City", "lat": 14.64, "lon": -90.52},
  {"name": "San José", "lat": 9.93, "lon": -84.08},
  {"name": "Panama City", "lat": 8.99, "lon": -79.52},
  {"name": "São Paulo", "lat": -23.55, "lon": -46.63},
  {"name": "Buenos Aires", "lat": -34.61, "lon": -58.38},
  {"name": "Rio de Janeiro", "lat": -22.91, "lon": -43.17},
  {"name": "Bogotá", "lat": 4.71, "lon": -74.07},
  {"name": "Lima", "lat": -12.05, "lon": -77.04},
  {"name": "Santiago", "lat": -33.45, "lon": -70.67},
  {"name": "Caracas", "lat": 10.49, "lon": -66.88},
  {"name": "Brasília", "lat": -15.78, "lon": -47.93},
  {"name": "Montevideo", "lat": -34.90, "lon": -56.17},
  {"name": "Quito", "lat": -0.23, "lon": -78.52},
  {"name": "La Paz", "lat": -16.50, "lon": -68.15},
  {"name": "Asunción", "lat": -25.29, "lon": -57.65},
  {"name": "Tokyo", "lat": 35.69, "lon": 139.69},
  {"name": "Beijing", "lat": 39.91, "lon": 116.39},
  {"name": "Shanghai", "lat": 31.23, "lon": 121.47},
  {"name": "Delhi", "lat": 28.66, "lon": 77.21},
  {"name": "Mumbai", "lat": 19.08, "lon": 72.88},
  {"name": "Jakarta", "lat": -6.21, "lon": 106.85},
  {"name": "Seoul", "lat": 37.57, "lon": 126.98},
  {"name": "Bangkok", "lat": 13.75, "lon": 100.52},
  {"name": "Karachi", "lat": 24.86, "lon": 67.01},
  {"name": "Dhaka", "lat": 23.72, "lon": 90.41},
  {"name": "Osaka", "lat": 34.69, "lon": 135.50},
  {"name": "Kolkata", "lat": 22.57, "lon": 88.36},
  {"name": "Manila", "lat": 14.60, "lon": 120.98},
  {"name": "Tehran", "lat": 35.69, "lon": 51.42},
  {"name": "Baghdad", "lat": 33.34, "lon": 44.40},
  {"name": "Singapore", "lat": 1.29, "lon": 103.85},
  {"name": "Kuala Lumpur", "lat": 3.15, "lon": 101.69},
  {"name": "Ho Chi Minh City", "lat": 10.82, "lon": 106.63},
  {"name": "Taipei", "lat": 25.04, "lon": 121.53},
  {"name": "Hong Kong", "lat": 22.33, "lon": 114.19},
  {"name": "Yangon", "lat": 16.87, "lon": 96.20},
  {"name": "Kathmandu", "lat": 27.72, "lon": 85.32},
  {"name": "Colombo", "lat": 6.93, "lon": 79.85},
  {"name": "Kabul", "lat": 34.52, "lon": 69.18},
  {"name": "Tashkent", "lat": 41.30, "lon": 69.27},
  {"name": "Almaty", "lat": 43.26, "lon": 76.95},
  {"name": "Ulaanbaatar", "lat": 47.91, "lon": 106.88},
  {"name": "Islamabad", "lat": 33.72, "lon": 73.06},
  {"name": "Hanoi", "lat": 21.03, "lon": 105.85},
  {"name": "Phnom Penh", "lat": 11.56, "lon": 104.92},
  {"name": "Vientiane", "lat": 17.97, "lon": 102.61},
  {"name": "Riyadh", "lat": 24.69, "lon": 46.72},
  {"name": "Dubai", "lat": 25.20, "lon": 55.27},
  {"name": "Amman", "lat": 31.96, "lon": 35.95},
  {"name": "Beirut", "lat": 33.89, "lon": 35.50},
  {"name": "Tel Aviv", "lat": 32.08, "lon": 34.78},
  {"name": "Doha", "lat": 25.29, "lon": 51.53},
  {"name": "Kuwait City", "lat": 29.37, "lon": 47.98},
  {"name": "Muscat", "lat": 23.61, "lon": 58.59},
  {"name": "Sanaa", "lat": 15.35, "lon": 44.21},
  {"name": "Cairo", "lat": 30.05, "lon": 31.25},
  {"name": "Lagos", "lat": 6.46, "lon": 3.38},
  {"name": "Kinshasa", "lat": -4.32, "lon": 15.32},
  {"name": "Johannesburg", "lat": -26.20, "lon": 28.04},
  {"name": "Nairobi", "lat": -1.29, "lon": 36.82},
  {"name": "Dar es Salaam", "lat": -6.82, "lon": 39.29},
  {"name": "Addis Ababa", "lat": 9.03, "lon": 38.74},
  {"name": "Khartoum", "lat": 15.55, "lon": 32.53},
  {"name": "Dakar", "lat": 14.73, "lon": -17.47},
  {"name": "Accra", "lat": 5.56, "lon": -0.20},
  {"name": "Casablanca", "lat": 33.59, "lon": -7.62},
  {"name": "Luanda", "lat": -8.84, "lon": 13.23},
  {"name": "Kampala", "lat": 0.32, "lon": 32.58},
  {"name": "Harare", "lat": -17.83, "lon": 31.05},
  {"name": "Tunis", "lat": 36.82, "lon": 10.17},
  {"name": "Algiers", "lat": 36.74, "lon": 3.06},
  {"name": "Abidjan", "lat": 5.35, "lon": -4.00},
  {"name": "Maputo", "lat": -25.97, "lon": 32.59},
  {"name": "Kigali", "lat": -1.94, "lon": 30.06},
  {"name": "Antananarivo", "lat": -18.91, "lon": 47.54},
  {"name": "Cape Town", "lat": -33.93, "lon": 18.42},
  {"name": "Tripoli", "lat": 32.90, "lon": 13.18},
  {"name": "Bamako", "lat": 12.65, "lon": -8.00},
  {"name": "Ouagadougou", "lat": 12.36, "lon": -1.53},
  {"name": "Mogadishu", "lat": 2.05, "lon": 45.34},
  {"name": "Sydney", "lat": -33.87, "lon": 151.21},
  {"name": "Melbourne", "lat": -37.81, "lon": 144.97},
  {"name": "Brisbane", "lat": -27.47, "lon": 153.02},
  {"name": "Perth", "lat": -31.95, "lon": 115.86},
  {"name": "Auckland", "lat": -36.86, "lon": 174.77},
  {"name": "Wellington", "lat": -41.29, "lon": 174.78},
  {"name": "Suva", "lat": -18.14, "lon": 178.44},
  {"name": "Port Moresby", "lat": -9.44, "lon": 147.18}
]
